doom_chan/__init__.py
doom_chan/doom_chan.py
doom_chan-1.0.0.data/data/Lib/site-packages/doom_chan/libmpv-2.dll
doom_chan-1.0.0.dist-info/METADATA
doom_chan-1.0.0.dist-info/WHEEL
doom_chan-1.0.0.dist-info/entry_points.txt
doom_chan-1.0.0.dist-info/top_level.txt
doom_chan-1.0.0.dist-info/RECORD
