Metadata-Version: 2.1
Name: doom_chan
Version: 1.0.0
Summary: Turns 4chan threads into "doomscrollable" playlists
Keywords: 4chan,video,CLI,mpv,doom scroll
Requires-Python: >=3.10
Requires-Dist: requests
Requires-Dist: beautifulsoup4
Requires-Dist: python-mpv
Requires-Dist: colorama
Requires-Dist: cowsay
